Workbook

Sheet Application_form
A1: Application ID: | G1: (For office use)
A3: APPLICATION FORM FOR FINANCIAL ASSISTANCE UNDER PRIME MINISTERS EMPLOYMENT GENERATION PROGRAMME (PMEGP)
T21: Khadi & V.I. Commission
T22: Khadi & V.I.Board
T23: District Industries Center
T24: District Industries Center
A54: 12 | B54: Name of the project / business activity proposed :
A56: 13 | B56: Amount of loan required (in Rs.)
B57: Building Type | C57: Capital Expenditure Loan
C58: Workshed Building etc. | D58: Machinery/ Equipment/Furniture | E58: Pre Operative Cost | F58: Working Capital / Cash Credit Limit | G58: Total
B59: =INDEX(DataSheet!L91:L93,DataSheet!M91,B1) -> Rented | C59: =DataSheet!H48 -> 0 | D59: =DataSheet!H67+DataSheet!H72 -> 0 | E59: =DataSheet!H70+DataSheet!H74 -> 0 | F59: =DataSheet!H76 -> 0 | G59: =SUM(C59:F59) -> 0
A60: 14 | B60: Details of earlier or current Loan/Grant and subsidy availed from Central/State Govt. Scheme/ or any other Similar Scheme.
B61: Activity of the Project with Address | E61: Amount | F61: Year of Sanction
B63: I certify that all information furnished by me is true; and that I and any of my dependent have not borrowed any money under subsidy linked scheme from any Central / State Government or bank for establishing any such project
B65: Place:
B66: Date: | G66: Signature of the Applicant
B68: For Official Use only: | D68: (Rejected / to be placed before District Task force Committee)
B69: Reason (if Rejected):
B72: Place: | F72: Signature, Name & Designation of Officer
B73: Date:
B76: NOTE
B77: • Own contribution must be invested 5% for SC/ST/OBC/PHC/woman/ Ex-serviceman/ North East Reason/Hill Boarder Area and 10% for General • Total Project Cost should not exceed 25 lakhs for Manufacturing unit and 10 lakhs for service unit. • Applicant will not be entitled for additional Margin Money(Subsidy) in case of Own Contribution over and above the prescribed limit. • VIIIth pass for Manufacturing Unit above Rs.10 lakhs project cost and under Service Sector above Rs.5 lakhs • Application should be submitted complete in all respect along with attested copies of the following documents: 1. Certificate of qualification-academic and technical (if project cost above 5 lakhs under service industry or above 10 lakhs under Manufacturing industry) 2. Relevant Certificate for SC/ST/OBC/Minority/Ex-Servicemen/PHC 3. if Entrepreneur Development programme(EDP) training undergone (at least for two weeks) then submit photocopy of the certificate

Sheet DataSheet
A1: DATA INPUT SHEET
A5: Preference for sponsoring agency of the project : | H5: (mark √ )
A6: Unit Location (As per revenue record) : | H6: (mark √ )
B7: KVIC | C7: =IF(DataSheet!M59=1,"√"," ") -> √ | D7: KVIB | E7: =IF(DataSheet!M59=2,"√"," ") | F7: DIC | G7: =IF(DataSheet!M59=3,"√"," ") | H7: COIR Board | J7: =IF(DataSheet!M59=4,"√"," ")
A8: 1.1 | B8: Name of the Applicant/Institution
A10: 1.2
A12: 2 | B12: Gender | D12: Male | E12: =IF(DataSheet!M55=1,"√"," ") -> √ | F12: Female | G12: =IF(DataSheet!M55=2,"√"," ") | H12: Transgender | I12: =IF(DataSheet!M55=3,"√"," ")
A13: 3 | B13: Address of the Proposed location of Unit: | F13: Rural | G13: =IF(DataSheet!M64=1,"√"," ") -> √ | H13: Urban | I13: =IF(DataSheet!M64<>1,"√"," ")
B16: Taluk/Block:
B17: District: | G17: Pin:
B18: State:
B19: Email: | F19: Mobile: | U19: Urban
A21: 4 | B21: Qualification
B22: Academic | E22: Technical
B23: =INDEX(DataSheet!L83:L89,DataSheet!M83) -> 12th Pass
A25: 5 | B25: Whether the applicant belongs to (mark √) | L25: =IF(DataSheet!M59=4,IF(AND(DataSheet!M56=1,DataSheet!M70=8),15%,25%),IF(AND(DataSheet!M56=1,DataSheet!M70=8),25%,35%)) -> 0.35
B26: SC | C26: ST | D26: OBC | E26: PHC | F26: Ex- Service man | G26: Minority | H26: Hill Border Area | I26: Aspirational Districts | J26: General
B27: =IF(DataSheet!M70=1,"√"," ") -> √ | C27: =IF(DataSheet!M70=2,"√"," ") | D27: =IF(DataSheet!M70=3,"√"," ") | E27: =IF(DataSheet!M70=4,"√"," ") | F27: =IF(DataSheet!M70=5,"√"," ") | G27: =IF(DataSheet!M70=6,"√"," ") | H27: =IF(DataSheet!M70=7,"√"," ") | I27: =IF(DataSheet!M70=8,"√"," ") | J27: =IF(DataSheet!M70=9,"√"," ")
A29: 6 | B29: Whether the project (mark √) | F29: Manufacturing Unit | G29: =IF(DataSheet!M80=1,"√"," ") -> √ | H29: Service Unit | I29: =IF(DataSheet!M80=2,"√"," ")
A31: 8 | B31: Name of the project / business activity proposed :
B34: Legal Status:
B36: Land | M36: =L59:L62 -> #VALUE!
B39: BUILDING DETAILS
B40: Particulars | F40: Area | G40: Rate/Sq.ft | H40: Amount in Rs.
B41: 2 Floor Building | H41: =IF(F41>=1,F41*G41,G41) -> 0
H42: =IF(F42>=1,F42*G42,G42) -> 0
H43: =IF(F43>=1,F43*G43,G43) -> 0
H44: =IF(F44>=1,F44*G44,G44) -> 0
H45: =IF(F45>=1,F45*G45,G45) -> 0
H46: =IF(F46>=1,F46*G46,G46) -> 0
H47: =IF(F47>=1,F47*G47,G47) -> 0
H48: =SUM(H41:H47) -> 0
B52: MACHINERY DETAILS
B53: Particulars | F53: Qty. | G53: Rate | H53: Amount in Rs.
B54: CNC | H54: =IF(F54>=1,F54*G54,G54) -> 0
H55: =IF(F55>=1,F55*G55,G55) -> 0 | L55: Male | M55: 1 | Q55: =IF(IF(AND(DataSheet!M55=1,DataSheet!M70=9,DataSheet!M64=2),15%,25%),IF(AND(DataSheet!M55=1,DataSheet!M70=9,DataSheet!M64=1),25%,35%)) -> 0.35
H56: =IF(F56>=1,F56*G56,G56) -> 0 | L56: Female
H57: =IF(F57>=1,F57*G57,G57) -> 0 | L57: Transgender | R57: =IF(M64=2,IF(AND(M55=1,M70=9),15,25),IF(AND(M55=1,M70=9),25,35)) -> 35
H58: =IF(F58>=1,F58*G58,G58) -> 0 | R58: =IF(AND(M55=1,M70=9,M64=2),15,25) -> 25
H59: =IF(F59>=1,F59*G59,G59) -> 0 | L59: KVIC | M59: 1 | R59: =IF(AND(M55=1,M64=1,M70=9),35,25) -> 25
H60: =IF(F60>=1,F60*G60,G60) -> 0 | L60: KVIB | R60: =IF(AND(M57=1,M72=9,M66=2),15,0) -> 0
H61: =IF(F61>=1,F61*G61,G61) -> 0 | L61: DIC | P61: 1
H62: =IF(F62>=1,F62*G62,G62) -> 0 | L62: COIR Board
H63: =IF(F63>=1,F63*G63,G63) -> 0
H64: =IF(F64>=1,F64*G64,G64) -> 0 | L64: Rural | M64: 1
H65: =IF(F65>=1,F65*G65,G65) -> 0 | L65: Urban
H66: =IF(F66>=1,F66*G66,G66) -> 0
B67: Total | H67: =SUM(H54:H66) -> 0 | L67: No | M67: 1
L68: Yes
B70: d. Preliminary & Pre-operative Cost : | L70: SC | M70: 1
L71: ST
B72: e. Furniture & Fixtures : | L72: OBC
L73: PHC
B74: f. Contingency/Others/Miscellaneous : | L74: Ex- Serviceman
L75: Minority
B76: Working Capital : | H76: =SUM(H70:I74) -> 0 | L76: Hill Boarder Area
L77: Aspirational Districts
L78: General
L80: Manufacturing | M80: 1
L81: Service
B83: Means of Financing | L83: Under 8th | M83: 4
L84: 8th Pass
B85: Own Contribution : | G85: =IF(AND(DataSheet!M55=1,DataSheet!M70=9),10%,5%) -> 0.05 | L85: 10th Pass
B86: Bank Finance : | G86: =100%-G85 -> 0.95 | L86: 12th Pass
B87: Margin Money (Govt. Subsidy) : | G87: =IF(DataSheet!M64=2,IF(AND(DataSheet!M55=1,DataSheet!M70=9),15%,25%),IF(AND(DataSheet!M55=1,DataSheet!M70=9),25%,35%)) -> 0.35 | L87: Graduate
L88: Post Graduate
L89: PhD
B91: DETAILS OF SALES | L91: Own | M91: 2
B92: Particulars of Products | F92: Rate/ | G92: Qantity | H92: Amount in Rs. | L92: Rented
F93: Unit | L93: Leased
H94: =IF(G94>=1,G94*F94,F94) -> 0
H95: =IF(G95>=1,G95*F95,F95) -> 0
H96: =IF(G96>=1,G96*F96,F96) -> 0
H97: =IF(G97>=1,G97*F97,F97) -> 0
H98: =IF(G98>=1,G98*F98,F98) -> 0
H99: =IF(G99>=1,G99*F99,F99) -> 0
H100: =IF(G100>=1,G100*F100,F100) -> 0
H101: =IF(G101>=1,G101*F101,F101) -> 0
B102: Total | H102: =SUM(H94:H101) -> 0
B105: RAW MATERIALS
B106: Particulars | E106: Unit | F106: Rate/Unit | G106: Reqd. Unit | H106: Amount In Rs.
H107: =IF(G107>=1,G107*F107,F107) -> 0
H108: =IF(G108>=1,G108*F108,F108) -> 0
H109: =IF(G109>=1,G109*F109,F109) -> 0
H110: =IF(G110>=1,G110*F110,F110) -> 0
H111: =IF(G111>=1,G111*F111,F111) -> 0
H112: =IF(G112>=1,G112*F112,F112) -> 0
H113: =IF(G113>=1,G113*F113,F113) -> 0
H114: =IF(G114>=1,G114*F114,F114) -> 0
H115: =IF(G115>=1,G115*F115,F115) -> 0
B116: Total | H116: =SUM(H107:H115) -> 0
B118: WAGES
B119: Particulars | E119: No. of | F119: Wages Per Month | H119: Amount in Rs.
E120: Worker | F120: Total Month | G120: 12
B121: Labor | H121: =E121*F121*G120 -> 0
H122: =E122*F122*G120 -> 0
H123: =E123*F123*G120 -> 0
H124: =E124*F124*G120 -> 0
H125: =E125*F125*G120 -> 0
H126: =E126*F126*G120 -> 0
...

Sheet DPR_print
B1: PROJECT AT A GLANCE - TOP SHEET
A3: 1 | B3: =Project_Report!B9 -> Name of the Beneficiary | E3: =Project_Report!G9 -> 0
A6: 2 | B6: =Project_Report!B11 -> Constitution (legal Status) : | E6: =Project_Report!G11 -> Individual
A8: 3 | B8: =Project_Report!B14 -> Father's/Spouce's Name | E8: =DataSheet!B11 -> 0
A10: 4 | B10: =Project_Report!B16 -> Unit Address : | E10: =Project_Report!G16 -> 0
E11: =Project_Report!G17 -> 0
E12: =Project_Report!G18 -> Taluk/Block: | F12: =Project_Report!H18 -> 0
E13: =Project_Report!G19 -> District : | F13: =Project_Report!H19 -> 0
E14: =Project_Report!G20 -> Pin: | F14: =Project_Report!H20 -> 0 | G14: =Project_Report!I20 -> State: | H14: =DataSheet!C18 -> 0
E15: =Project_Report!G22 -> E-Mail : | F15: =DataSheet!C19 -> 0
E16: Mobile | F16: =DataSheet!G19 -> 0
A17: 5 | B17: Product and By Product | E17: =DPR_FRONT!B2
A19: 6 | B19: Cost of Project | D19: : | E19: Rs. | F19: =H119 -> 0
B20: Name of the project / business activity proposed : | E20: =DataSheet!B32 -> 0
A22: 7 | B22: Means of Finance
B23: Term Loan | E23: Rs. | F23: =H129 -> 0
B24: KVIC Margin Money | E24: Rs. | F24: =H131 -> 0
B25: Own Capital | E25: Rs. | F25: =H123 -> 0
A28: 8 | B28: Debt Service Coverage Ratio | D28: :
A31: 9 | B31: Pay Back Period | D31: : | F31: =DataSheet!F179 -> 5 | G31: Years
A34: 10 | B34: Project Implementation Period | D34: : | F34: =DataSheet!G181 -> 0 | G34: Months
A37: 11 | B37: Break Even Point | D37: :
A40: 12 | B40: Employment | D40: : | F40: =Project_Report!I69 -> 0
A43: 13 | B43: Power Requirement | D43: : | F43: =DataSheet!G154 -> 0
A46: 14 | B46: Major Raw materials | D46: : | E46: =DataSheet!B107&","&DataSheet!B108&","&DataSheet!B109 -> ,,
A48: 15 | B48: Estimated Annual Sales Turnover | D48: : | E48: Rs. | F48: =H191 -> 0
A50: DETAILED PROJECT REPORT
A51: 1 | B51: INTRODUCTION :
B53: =DataSheet!B234 -> 0
A67: 2 | B67: ABOUT THE BENEFICIARY :
B69: =DataSheet!B251 -> 0
A81: 3 | B81: COST OF PROJECT
B82: A. Fixed Capital Investment
B83: a. Land : | F83: =DataSheet!F36:G36 -> 0 | H83: Own
B85: b. Workshed | F85: Area Sq.ft | G85: Rate in Rs. | H85: Amt. In Rs.
B86: =DataSheet!B41:E41 -> 2 Floor Building | F86: =DataSheet!F41 -> 0 | G86: =DataSheet!G41 -> 0 | H86: =DataSheet!H41:I41 -> 0
B87: =DataSheet!B42:E42 -> 0 | F87: =DataSheet!F42 -> 0 | G87: =DataSheet!G42 -> 0 | H87: =DataSheet!H42:I42 -> 0
B88: =DataSheet!B43:E43 -> 0 | F88: =DataSheet!F43 -> 0 | G88: =DataSheet!G43 -> 0 | H88: =DataSheet!H43:I43 -> 0
B89: =DataSheet!B44:E44 -> 0 | F89: =DataSheet!F44 -> 0 | G89: =DataSheet!G44 -> 0 | H89: =DataSheet!H44:I44 -> 0
B90: =DataSheet!B45:E45 -> 0 | F90: =DataSheet!F45 -> 0 | G90: =DataSheet!G45 -> 0 | H90: =DataSheet!H45:I45 -> 0
B91: =DataSheet!B46:E46 -> 0 | F91: =DataSheet!F46 -> 0 | G91: =DataSheet!G46 -> 0 | H91: =DataSheet!H46:I46 -> 0
B92: =DataSheet!B47:E47 -> 0 | F92: =DataSheet!F47 -> 0 | G92: =DataSheet!G47 -> 0 | H92: =DataSheet!H47:I47 -> 0
B93: Total | H93: =SUM(H86:H92) -> 0
B94: =#REF! -> #REF!
B95: C. Machinery | F95: Qty. | G95: Rate | H95: Amount in Rs.
B96: =DataSheet!B54:E54 -> CNC | F96: =DataSheet!F54 -> 0 | G96: =DataSheet!G54 -> 0 | H96: =DataSheet!H54:I54 -> 0
B97: =DataSheet!B55:E55 -> 0 | F97: =DataSheet!F55 -> 0 | G97: =DataSheet!G55 -> 0 | H97: =DataSheet!H55:I55 -> 0
B98: =DataSheet!B56:E56 -> 0 | F98: =DataSheet!F56 -> 0 | G98: =DataSheet!G56 -> 0 | H98: =DataSheet!H56:I56 -> 0
B99: =DataSheet!B57:E57 -> 0 | F99: =DataSheet!F57 -> 0 | G99: =DataSheet!G57 -> 0 | H99: =DataSheet!H57:I57 -> 0
B100: =DataSheet!B58:E58 -> 0 | F100: =DataSheet!F58 -> 0 | G100: =DataSheet!G58 -> 0 | H100: =DataSheet!H58:I58 -> 0
B101: =DataSheet!B59:E59 -> 0 | F101: =DataSheet!F59 -> 0 | G101: =DataSheet!G59 -> 0 | H101: =DataSheet!H59:I59 -> 0
B102: =DataSheet!B60:E60 -> 0 | F102: =DataSheet!F60 -> 0 | G102: =DataSheet!G60 -> 0 | H102: =DataSheet!H60:I60 -> 0
B103: =DataSheet!B61:E61 -> 0 | F103: =DataSheet!F61 -> 0 | G103: =DataSheet!G61 -> 0 | H103: =DataSheet!H61:I61 -> 0
B104: =DataSheet!B62:E62 -> 0 | F104: =DataSheet!F62 -> 0 | G104: =DataSheet!G62 -> 0 | H104: =DataSheet!H62:I62 -> 0
B105: =DataSheet!B63:E63 -> 0 | F105: =DataSheet!F63 -> 0 | G105: =DataSheet!G63 -> 0 | H105: =DataSheet!H63:I63 -> 0
B106: =DataSheet!B64:E64 -> 0 | F106: =DataSheet!F64 -> 0 | G106: =DataSheet!G64 -> 0 | H106: =DataSheet!H64:I64 -> 0
B107: =DataSheet!B65:E65 -> 0 | F107: =DataSheet!F65 -> 0 | G107: =DataSheet!G65 -> 0 | H107: =DataSheet!H65:I65 -> 0
B108: Total | H108: =DataSheet!H67:I67 -> 0
B109: =DataSheet!B70:E70 -> d. Preliminary & Pre-operative Cost : | G109: Rs. | H109: =DataSheet!H70:I70 -> 0
B111: =DataSheet!B72:E72 -> e. Furniture & Fixtures : | G111: Rs. | H111: =DataSheet!H72:I72 -> 0
B113: =DataSheet!B74:E74 -> f. Contingency/Others/Miscellaneous : | G113: Rs. | H113: =DataSheet!H74:I74 -> 0
B115: Total Capital Expenditure : | G115: Rs. | H115: =H93+H108+H109+H111+H113 -> 0
B117: =DataSheet!B76:E76 -> Working Capital : | G117: Rs. | H117: =ROUND((H290),0) -> 0
B119: Total Cost Project : | G119: Rs. | H119: =H93+H108+H109+H111+H113+H117 -> 0
A122: 3.1 | B122: Means of Financing :
B123: Own Contribution | F123: =DataSheet!G85 -> 0.05 | G123: Rs. | H123: =ROUND((F123*H119),0) -> 0
B125: Bank Finance : | F125: =DataSheet!G86 -> 0.95
B126: Term Loan | G126: Rs. | H126: =ROUND((F125*H115),0) -> 0
B127: Working Capital | G127: Rs. | H127: =ROUND((F125*H117),0) -> 0
B129: Total | G129: Rs. | H129: =ROUND((H126+H127),0) -> 0
B131: Margin Money (Govt. Subsidy) From KVIC | F131: =DataSheet!G87 -> 0.35 | G131: Rs. | H131: =IF(AND(DataSheet!M83=1,DataSheet!M80=2,H119>500000),"Should not exceed Rs. 5 lakhs Project cost under under Service Industry",IF(AND(DataSheet!M83=1,DataSheet!M80=1,H119>1000000),"Should not exceed Rs. 10 lakhs Project cost under Manufacturing Industry",IF(AND(DataSheet!M83>1,DataSheet!M80=2,H119>2000000),ROUND(2000000*F131,0),IF(AND(DataSheet!M83>1,DataSheet!M80=1,H119>5000000),ROUND(5000000*F131,0),ROUND(H119*F131,0))))) -> 0 | J131: =IF(AND(DataSheet!M83>1,DataSheet!M80=2,H119>2000000),"The maximum project cost eligible for subsidy is Rs. 20 lakhs under Service Industry",IF(AND(DataSheet!M83>1,DataSheet!M80=1,H119>5000000),"The maximum project cost eligible for subsidy is Rs. 50 Lakhs under Manufacturing Industry",TRUE())) -> 1
B132: Margin Money Subsidy received From KVIC will be kept in term deposit as per norms of
B133: PMEGP in the name of Beneficiary for three years in the financing branch.
A137: 3.2 | B137: STATEMENT SHOWING THE REPAYMENT OF TERM LOAN & WORKING CAPITAL :
B138: TERM LOAN
B140: Year | C140: Opening Balance | F140: Installment | G140: Closing Balance | I140: Interest @
I141: =DataSheet!F173 -> 0
B142: 1st | C142: =H126 -> 0 | F142: =C142*F34/12*1/F31 -> 0 | G142: =C142-F142 -> 0 | I142: =C142*I141 -> 0
B143: 2nd | C143: =G142 -> 0 | F143: =C142/F31 -> 0 | G143: =C143-F143 -> 0 | I143: =C143*I141 -> 0
B144: 3rd | C144: =G143 -> 0 | F144: =C142/F31 -> 0 | G144: =C144-F144 -> 0 | I144: =C144*I141 -> 0
B145: 4th | C145: =G144 -> 0 | F145: =C142/F31 -> 0 | G145: =C145-F145 -> 0 | I145: =C145*I141 -> 0
B146: 5th | C146: =G145 -> 0 | F146: =C142/F31 -> 0 | G146: =C146-F146 -> 0 | I146: =C146*I141 -> 0
B147: 6th | C147: =G146 -> 0 | F147: =IF(C147>0,C142/F31,0) -> 0 | G147: =IF(F147>C147,0,C147-F147) -> 0 | I147: =C147*I141 -> 0
B148: 7th | C148: =G147 -> 0 | F148: =IF(C148>0,C142/F31,0) -> 0 | G148: =IF(F148>C148,0,C148-F148) -> 0 | I148: =C148*I141 -> 0
B149: 8th | C149: =G148 -> 0 | F149: =IF(C149>0,C142/F31,0) -> 0 | G149: =IF(F149>C149,0,C149-F149) -> 0 | I149: =C149*I141 -> 0
A151: WORKING CAPITAL
B153: Year | C153: Opening Balance | F153: Installment | G153: Closing Balance | I153: Interest @
I154: =DataSheet!F173 -> 0
B155: 1st | C155: =H127 -> 0 | F155: =C155*F34/12*1/F31 -> 0 | G155: =C155-F155 -> 0 | I155: =C155*I154 -> 0
B156: 2nd | C156: =G155 -> 0 | F156: =C155/F31 -> 0 | G156: =C156-F156 -> 0 | I156: =C156*I154 -> 0
B157: 3rd | C157: =G156 -> 0 | F157: =C155/F31 -> 0 | G157: =C157-F157 -> 0 | I157: =C157*I154 -> 0
B158: 4th | C158: =G157 -> 0 | F158: =C155/F31 -> 0 | G158: =C158-F158 -> 0 | I158: =C158*I154 -> 0
B159: 5th | C159: =G158 -> 0 | F159: =C155/F31 -> 0 | G159: =C159-F159 -> 0 | I159: =C159*I154 -> 0
B160: 6th | C160: =G159 -> 0 | F160: =IF(C160>0,C155/F31,0) -> 0 | G160: =IF(F160>C160,0,C160-F160) -> 0 | I160: =C160*I154 -> 0
B161: 7th | C161: =G160 -> 0 | F161: =IF(C161>0,C155/F31,0) -> 0 | G161: =IF(F161>C161,0,C161-F161) -> 0 | I161: =C161*I154 -> 0
B162: 8th | C162: =G161 -> 0 | F162: =IF(C162>0,C155/F31,0) -> 0 | G162: =IF(F162>C162,0,C162-F162) -> 0 | I162: =C162*I154 -> 0
A163: 3.3 | B163: STATEMENT SHOWING THE DEPRECIATION ON FIXED ASSETS:
B164: WORKSHED | H164: @ | I164: =DataSheet!F176 -> 0
B165: Particulars | E165: 1st Year | F165: 2nd Year | G165: 3rd Year | H165: 4th Year | I165: 5th Year
B166: Opening Balance | E166: =H93 -> 0 | F166: =E168 -> 0 | G166: =F168 -> 0 | H166: =G168 -> 0 | I166: =H168 -> 0
...

Sheet Project_Report
A1: PROJECT REPORT FOR
A2: =UPPER(Application_form!B55)
I5: Affix latest
I6: attested
I7: Photograph
A9: 1 | B9: =IF(K10=1,"Name of the Beneficiary","Name of the Institution/Unit") -> Name of the Beneficiary | G9: =DataSheet!B9 -> 0
K10: 1 | M10: Individual
A11: 2 | B11: Constitution (legal Status) : | G11: =INDEX(M10:M14,K10) -> Individual
A14: 3 | B14: =IF(K10=1,"Father's/Spouce's Name","Contact Persons Name") -> Father's/Spouce's Name | G14: =#REF! -> #REF!
A16: 5 | B16: Unit Address : | G16: =DataSheet!B14 -> 0
G17: =DataSheet!B15 -> 0
G18: Taluk/Block: | H18: =DataSheet!D16 -> 0
G19: District : | H19: =DataSheet!D16 -> 0
G20: Pin: | H20: =DataSheet!H17 -> 0 | I20: State: | J20: =#REF! -> #REF!
G21: Phone : | H21: =#REF! -> #REF!
G22: E-Mail : | H22: =#REF! -> #REF!
A24: 6 | B24: Background of the Proprietor/Partners/Directors : | G24: Furnished detailed information in the DPR
A27: 7 | B27: Name of Business House/Group if any :
A31: 8 | B31: Details Other Companies/Units in the group :
B32: Other Companies / Units in the Group | I32: (Rs. in Lakhs)
B33: Name & Address | D33: Business | E33: Equity | F33: Reserves | G33: Loans | H33: Turnover | I33: *P.B.T | J33: **P.A.T
B34: of Company / Unit
B37: * Profit Before Tax | D37: ** Profit After Tax
E38: `
A41: 8.1 | B41: How the activity was financed so far : | F41: ( To be filled up in case of existining unit Only )
B42: *Source of Funds | D42: Security | E42: Rate of | F42: Repayment per | H42: Present O/s | J42: Amount of Default
E43: Interest | F43: Month | H43: ( Rs. in '000 ) | J43: (if any)
A50: 8.2 | B50: If the Unit is an ancillary one, undertaking to
B51: which it is catering and its address :
A56: 8.3 | B56: Employment : | G56: Present | I56: Proposed
B57: =DataSheet!B121:D121 -> Labor | I57: =DataSheet!E121 -> 0
B58: =DataSheet!B122:D122 -> 0 | I58: =DataSheet!E122 -> 0
B59: =DataSheet!B123:D123 -> 0 | I59: =DataSheet!E123 -> 0
B60: =DataSheet!B124:D124 -> 0 | I60: =DataSheet!E124 -> 0
B61: =DataSheet!B125:D125 -> 0 | I61: =DataSheet!E125 -> 0
B62: =DataSheet!B126:D126 -> 0 | I62: =DataSheet!E126 -> 0
B63: =DataSheet!B127:D127 -> 0 | I63: =DataSheet!E127 -> 0
B64: =DataSheet!B134:D134 -> 0 | I64: =DataSheet!E134 -> 0
B65: =DataSheet!B135:D135 -> 0 | I65: =DataSheet!E135 -> 0
B66: =DataSheet!B136:D136 -> 0 | I66: =DataSheet!E136 -> 0
B67: =DataSheet!B137:D137 -> 0 | I67: =DataSheet!E137 -> 0
B68: =DataSheet!B138:D138 -> 0 | I68: =DataSheet!E138 -> 0
B69: Total | I69: =SUM(I57:I68) -> 0
A72: 9 | B72: Project Details for Proposed New Unit : | G72: Copy of detailed project report is enclosed.
B73: a | C73: Expansion / Mordenisation :
B75: b | C75: Setting up of New unit :
B77: c | C77: Activity for proposed new unit :
B79: d | C79: Product / Item proposed to undertake :
A82: 9.1 | B82: Capacity (Furnish the details of Installed capacity & production : | H82: (No. in Units/ Qty. in Kg./Volume in liter per annum)
B83: Capacity is arrived at on the basis of | G83: Days working on | J83: shift basis
B84: Product & | D84: Present Installed | F84: Maximum Prod. | H84: Proposed Installed | J84: Maximum Prod.
B85: By-product if any | D85: Capacity | F85: Achieved | H85: Capacity of 1st Year | J85: envisaged
H86: 0.7 | J86: =DPR_print!F303 -> 0
A94: 9.3 | B94: State the manufacturing process in brief :
A105: 9.4 | B105: Has the proposed process ever been tried in the
B106: country or newly adopted? :
A112: 9.5 | B112: Technical Arrangements :
A122: 9.6 | B122: Describe arrangement for Key Official
B123: for managing the proposed unit :
B124: Technical Manpower
B126: Administrative Manpower
B128: Accounting personnel
A132: 9.7 | B132: Particulars of Land | F132: Existing | I132: Proposed
B133: Location of the Land :
B134: Area of Land :
B135: Status of the Land :
B136: Nature of Land :
B137: Availability of Water :
A140: 9.8 | B140: Particulars of Building | F140: Existing | I140: Proposed
B141: (Enclose the plan & Estimation for the proposed Building) | F141: Area | G141: Value in Rs. | H141: Status | I141: Area | J141: Value | K141: Status
B142: Factory Building :
B144: Ancillary Building :
B146: Storage :
B148: Total : | G148: =G142+G144+G146 -> 0 | J148: =J142+J144+J146 -> 0
A151: 9.9 | B151: Plant and Machinery | F151: Existing (Value in Rs.) | I151: Proposed (Value in Rs.)
B152: Indigenous | I152: =DPR_print!H108 -> 0
B154: Imported
B156: (Enclose the plan layout of the existing plant and machinery )
A159: 9.1 | B159: Rawmaterials / Components
B160: Req. of Raw material/Components/Chemicals | F160: Qty. in Nos./Kgs./Ton | H160: Rate/Nos./Kgs/Tons | J160: Value in Rs.
B167: Total | J167: =SUM(J161:J166) -> 0
A170: 9.11 | B170: Utilities (Furnish details on requirement, availability, adequacy, qualitative aspects etc..)
B171: Particulars of Utilities | F171: Contracted Load | H171: Connected Load | J171: Further requirement
F172: in HP/KW/W | H172: in HP/KW/W | J172: in HP/KW/W
B173: Power
B175: Water
B177: Fuel
B179: Others (Specify)
A187: 9.12 | B187: Environment Aspect of the Project :
A198: 9.13 | B198: Requirement of Manpower for the Project :
B199: Particulars of Manpower | F199: Total Requirement | H199: Salary/Wages per month | J199: Cost per Annum
B200: =B57 -> Labor | F200: =I57 -> 0 | H200: =DPR_print!F215 -> 0 | J200: =F200*H200*12 -> 0
B201: =B58 -> 0 | F201: =I58 -> 0 | H201: =DPR_print!F216 -> 0 | J201: =F201*H201*12 -> 0
B202: =B59 -> 0 | F202: =I59 -> 0 | H202: =DPR_print!F217 -> 0 | J202: =F202*H202*12 -> 0
B203: =B60 -> 0 | F203: =I60 -> 0 | H203: =DPR_print!F218 -> 0 | J203: =F203*H203*12 -> 0
B204: =B61 -> 0 | F204: =I61 -> 0 | H204: =DPR_print!F219 -> 0 | J204: =F204*H204*12 -> 0
B205: =B62 -> 0 | F205: =I62 -> 0 | H205: =DPR_print!F220 -> 0 | J205: =F205*H205*12 -> 0
B206: =B63 -> 0 | F206: =I63 -> 0 | H206: =DPR_print!F221 -> 0 | J206: =F206*H206*12 -> 0
B207: =B64 -> 0 | F207: =I64 -> 0 | H207: =DPR_print!F232 -> 0 | J207: =F207*H207*12 -> 0
B208: =B65 -> 0 | F208: =I65 -> 0 | H208: =DPR_print!F233 -> 0 | J208: =F208*H208*12 -> 0
...

Sheet DPR_FRONT
B1: Project Report on
B2: =UPPER(Application_form!B55)
B32: Prepared By:
B33: =#REF! -> #REF!
B34: =INDEX(Application_form!T21:T24,DataSheet!M59) -> Khadi & V.I. Commission
B35: =#REF! -> #REF!
B36: =#REF! -> #REF!
B37: =#REF! -> #REF! | E37: State: | F37: =#REF! -> #REF!
B38: e-Mail:
B39: Ph. No.: | F39: Fax:
